[
  {
    "id": 101,
    "title": "شاليه للبيع مشروع مورانو وادي دجلة",
    "developer": "مطور",
    "type": "قسط",
    "images": [
      "https://c.top4top.io/p_35249hfap2.jpg",
      "https://b.top4top.io/p_3524bqo0h1.jpg",
      "https://a.top4top.io/p_3524wj4b00.jpg",
      "https://d.top4top.io/p_35241i6053.jpg"
    ],
    "details": {
      "bedrooms": 3,
      "bathrooms": 2,
      "area": "125 م²"
    },
    "price": "9,500,000 جنيه",
    "payment": {
      "downPayment": "10%",
      "quarter": "115,000 جنيه",
      "installments": "95 قسط",
      "duration": "8 سنوات",
      "maintenance": "10%",
      "totalPrice": "9,500,000 جنيه",
      "delivery": "2027"
    },
    "description": "تُعد قرية مورانو العين السخنة ملاذاً هادئاً بعيدًا عن زحام وضوضاء المدينة وفي ذات الوقت تبعد مسافة ليست بالطويلة، فيمكن السفر منها وإليها بكل سهولة وفي وقت قياسي، فعلى شواطئ البحر الأحمر تُقدم مورانو تجربة فريدة تجمع بين سحر الطبيعة ورفاهية الحياة العصرية، وتم تصميم Murano Wadi Degla بعناية فائقة لتوفير بيئة استثنائية تُركز على الهدوء والسكينة، مع توفير كافة وسائل الراحة والترفيه حيث تتميز بموقعها الفريد ومرافقها المتنوعة، بالإضافة إلى وجود ينابيع مياه ساخنة طبيعية تُضيف لمسة مميزة إلى القرية.\n\nالموقع: تقع قرية مورانو في نهاية طريق العين السخنة وبداية طريق الزعفرانة، على بُعد 136 كيلو من القاهرة. قريبة من طريق الجلالة (18 كم) ومحطة قطار العين السخنة (14 كم).\n\nالمرافق: شاطئ رملي 750 متر، مارينا 100 متر، منتجع فندقي 4 نجوم، مطاعم وكافيهات، سبا، ملاعب رياضية، مناطق للأطفال، محلات تجارية، حمامات سباحة متنوعة.\n\nعن المطور: شركة وادي دجلة للتطوير العقاري تأسست عام 2005، ولها 16 مشروعًا بمساحة إجمالية 5.5 مليون متر مربع. أنجزت 12 مشروعًا وأكثر من 10,000 وحدة."
  }
]
